<?xml version="1.0" encoding="UTF-8"?>
<!DOCTYPE tiles-definitions PUBLIC 
    "-//Apache Software Foundation//DTD Tiles Configuration 3.0//EN" 
    "http://tiles.apache.org/dtds/tiles-config_2_1.dtd">

<tiles-definitions>
 
 <definition name="baseLayout" template="/WEB-INF/views/layout/layout.jsp">
  <put-attribute name="title" value="SivaLabs" />
  <put-attribute name="header" value="/WEB-INF/views/layout/header.jsp" />
  <put-attribute name="navigation" value="/WEB-INF/views/layout/navigation.jsp" />
  <put-attribute name="body" value="" />
  <put-attribute name="footer" value="/WEB-INF/views/layout/footer.jsp" />
 </definition>
  
 <definition name="login" extends="baseLayout">
  <put-attribute name="title" value="SivaLabs : Login" />
  <put-attribute name="navigation" value="" />
  <put-attribute name="body" value="/WEB-INF/views/login.jsp" />
 </definition>
   
 <definition name="welcome" extends="baseLayout">
  <put-attribute name="title" value="Welcome" />
  <put-attribute name="body" value="/WEB-INF/views/welcome.jsp" />
 </definition>
 
 <definition name="blogList" extends="baseLayout">
  <put-attribute name="title" value="Blog List" />
  <put-attribute name="body" value="/WEB-INF/views/blogList.jsp" />
 </definition>
 
 <definition name="addBlog" extends="baseLayout">
  <put-attribute name="title" value="Blog Add" />
  <put-attribute name="body" value="/WEB-INF/views/addBlog.jsp" />
 </definition>
 
 <definition name="blogDetail" extends="baseLayout">
  <put-attribute name="title" value="Blog Details" />
  <put-attribute name="body" value="/WEB-INF/views/blogDetail.jsp" />
 </definition>
   
</tiles-definitions>